{
  "project_info": {
    "project_number": "778994651749",
    "firebase_url": "https://customfcm-79cec.firebaseio.com",
    "project_id": "customfcm-79cec",
    "storage_bucket": "customfcm-79cec.appspot.com"
  },
  "client": [
    {
      "client_info": {
        "mobilesdk_app_id": "1:778994651749:android:069c80ddabeb5377",
        "android_client_info": {
          "package_name": "com.hosnydev.customfcm"
        }
      },
      "oauth_client": [
        {
          "client_id": "778994651749-pir564s7n4pu9dhsjovkej2ccbpac7fu.apps.googleusercontent.com",
          "client_type": 1,
          "android_info": {
            "package_name": "com.hosnydev.customfcm",
            "certificate_hash": "380935da015cdd60fbfec7c46069e76244743f12"
          }
        },
        {
          "client_id": "778994651749-v5llnsfero011gl3fr4c7321vlmtkh6s.apps.googleusercontent.com",
          "client_type": 3
        }
      ],
      "api_key": [
        {
          "current_key": "AIzaSyBdipd8RgAm8hi1eBYFyUgFie0QEprQ9ps"
        }
      ],
      "services": {
        "appinvite_service": {
          "other_platform_oauth_client": [
            {
              "client_id": "778994651749-v5llnsfero011gl3fr4c7321vlmtkh6s.apps.googleusercontent.com",
              "client_type": 3
            }
          ]
        }
      }
    }
  ],
  "configuration_version": "1"
}